rival_ai/__init__.py
rival_ai/config.py
rival_ai/exceptions.py
rival_ai/core/__init__.py
rival_ai/core/agent_definition.py
rival_ai/core/benchmarking.py
rival_ai/core/benchmarking_result.py
rival_ai/core/evaluation.py
rival_ai/core/testcase.py
rival_ai/evaluators/__init__.py
rival_ai/evaluators/local_evaluator.py
rival_ai/evaluators/prompts.py
rival_ai/generators/__init__.py
rival_ai/generators/attack_criteria.py
rival_ai/generators/testcase_generator.py
rival_ai/utils/__init__.py
rival_ai/utils/agent_representation.py
rival_ai/utils/llm.py
rival_ai/utils/parsing.py
rival_sdk-0.1.0.dist-info/METADATA
rival_sdk-0.1.0.dist-info/WHEEL
rival_sdk-0.1.0.dist-info/top_level.txt
rival_sdk-0.1.0.dist-info/RECORD
